README.rst
setup.cfg
setup.py
restypy/__init__.py
restypy/restypy.py
restypy.egg-info/PKG-INFO
restypy.egg-info/SOURCES.txt
restypy.egg-info/dependency_links.txt
restypy.egg-info/requires.txt
restypy.egg-info/top_level.txt