Metadata-Version: 1.1
Name: restypy
Version: 0.7
Summary: A Pythonic Rest API client
Home-page: https://github.com/simula67/restypy
Author: Joji Antony
Author-email: simula67@gmail.com
License: UNKNOWN
Download-URL: https://github.com/simula67/restypy/tarball/master
Keywords: rest,pythonic,client
Platform: UNKNOWN
